sumiBmi/BMI.py
sumiBmi-0.0.0.4.dist-info/METADATA
sumiBmi-0.0.0.4.dist-info/WHEEL
sumiBmi-0.0.0.4.dist-info/top_level.txt
sumiBmi-0.0.0.4.dist-info/RECORD
